tacape/__init__.py
tacape/logo.py
tacape/run_classifier.py
tacape/run_generator.py
tacape/train_classifier.py
tacape/train_generator.py
tacape/models/__init__.py
tacape/models/layers.py
tacape/models/model.py
tacape/utils/__init__.py
tacape/utils/load.py
tacape-0.0.6.dist-info/LICENSE
tacape-0.0.6.dist-info/METADATA
tacape-0.0.6.dist-info/WHEEL
tacape-0.0.6.dist-info/entry_points.txt
tacape-0.0.6.dist-info/top_level.txt
tacape-0.0.6.dist-info/RECORD
