Metadata-Version: 2.1
Name: tacape
Version: 0.0.6
Summary: TACaPe: Transformed-based Anti-Cancer Peptide Classification and Generation
Home-page: https://github.com/omixlab/anticancer-peptide
Author: Isadora Leitzke Guidotti, Frederico Schmitt Kremer
Author-email: fred.s.kremer@gmail.com
License: UNKNOWN
Keywords: bioinformatics machine-learning data science drug discovery QSAR
Platform: UNKNOWN
License-File: LICENSE
Requires-Dist: biopython
Requires-Dist: pandas
Requires-Dist: numpy
Requires-Dist: scikit-learn
Requires-Dist: tensorflow
Requires-Dist: tqdm
